pyava/__init__.py
pyava/cli.py
pyava/utils.py
pyavax-1.2.2.dist-info/licenses/LICENSE
pyavax-1.2.2.dist-info/METADATA
pyavax-1.2.2.dist-info/WHEEL
pyavax-1.2.2.dist-info/entry_points.txt
pyavax-1.2.2.dist-info/top_level.txt
pyavax-1.2.2.dist-info/RECORD
