Metadata-Version: 2.4
Name: pyavax
Version: 1.2.2
Summary: pyava is command line tool to help you check the availability of a package name you want on PyPI
Author-email: BirukBelihu <birukbelihu1995@email.com>
License: Apache-2.0
Project-URL: Homepage, https://github.com/birukbelihu/pyava
Project-URL: Source, https://github.com/birukbelihu/pyava
Project-URL: Issues, https://github.com/birukbelihu/pyava
Keywords: pypi,package checker,availability,cli
Classifier: Programming Language :: Python :: 3.9
Classifier: Programming Language :: Python :: 3.10
Classifier: Programming Language :: Python :: 3.11
Classifier: Programming Language :: Python :: 3.12
Classifier: Programming Language :: Python :: 3.13
Requires-Python: >=3.9
License-File: LICENSE
Requires-Dist: httpx
Requires-Dist: pyglowx
Dynamic: license-file
